ckanext/__init__.py
ckanext/search_schema/__init__.py
ckanext/search_schema/cli.py
ckanext/search_schema/const.py
ckanext/search_schema/exceptions.py
ckanext/search_schema/facades.py
ckanext/search_schema/interfaces.py
ckanext/search_schema/plugin.py
ckanext/search_schema/types.py
ckanext/search_schema/data/schema.json
ckanext/search_schema/data/default_schemas/solr8/copy-field.json
ckanext/search_schema/data/default_schemas/solr8/dynamic-field.json
ckanext/search_schema/data/default_schemas/solr8/field-type.json
ckanext/search_schema/data/default_schemas/solr8/field.json
ckanext/search_schema/tests/__init__.py
ckanext_search_schema-0.1.1.dist-info/LICENSE
ckanext_search_schema-0.1.1.dist-info/METADATA
ckanext_search_schema-0.1.1.dist-info/WHEEL
ckanext_search_schema-0.1.1.dist-info/entry_points.txt
ckanext_search_schema-0.1.1.dist-info/top_level.txt
ckanext_search_schema-0.1.1.dist-info/RECORD
